translatehtml/__init__.py
translatehtml/translatehtml.py
translatehtml-1.5.2.dist-info/LICENSE
translatehtml-1.5.2.dist-info/METADATA
translatehtml-1.5.2.dist-info/WHEEL
translatehtml-1.5.2.dist-info/top_level.txt
translatehtml-1.5.2.dist-info/RECORD
