Metadata-Version: 2.1
Name: translatehtml
Version: 1.5.2
Summary: Translate HTML using Beautiful Soup and Argos Translate
Home-page: https://www.argosopentech.com
Author: P.J. Finlay
Author-email: admin@argosopentech.com
License: UNKNOWN
Platform: UNKNOWN
